context.py
stackl.py
commands/__init__.py
commands/apply.py
commands/autocomplete.py
commands/connect.py
commands/create.py
commands/delete.py
commands/edit.py
commands/generate.py
commands/get.py
commands/info.py
commands/restore.py
commands/update.py
stackl_cli-0.5.1.dist-info/METADATA
stackl_cli-0.5.1.dist-info/WHEEL
stackl_cli-0.5.1.dist-info/entry_points.txt
stackl_cli-0.5.1.dist-info/top_level.txt
stackl_cli-0.5.1.dist-info/RECORD
