Metadata-Version: 2.1
Name: stackl-cli
Version: 0.5.1
Summary: UNKNOWN
Home-page: UNKNOWN
Author: UNKNOWN
Author-email: UNKNOWN
License: UNKNOWN
Platform: UNKNOWN
Requires-Dist: stackl-client (==0.5.0)
Requires-Dist: pyYAML (==5.4.1)
Requires-Dist: Click (==7.0)
Requires-Dist: mergedeep (==1.3.0)
Requires-Dist: tabulate (==0.8.6)
Requires-Dist: glom (==19.10.0)
